punit/TestResult.py
punit/__init__.py
punit/__main__.py
punit/cli.py
punit/runner.py
punit/assertions/__init__.py
punit/assertions/collections.py
punit/assertions/exceptions.py
punit/assertions/strings.py
punit/discovery/TestModuleDiscovery.py
punit/discovery/__init__.py
punit/facts/Fact.py
punit/facts/FactManager.py
punit/facts/__init__.py
punit/reports/HtmlReportGenerator.py
punit/reports/JUnitReportGenerator.py
punit/reports/__init__.py
punit/theories/Theory.py
punit/theories/TheoryManager.py
punit/theories/__init__.py
punit/traits/Trait.py
punit/traits/__init__.py
punit-1.1.4.dist-info/licenses/LICENSE
punit-1.1.4.dist-info/METADATA
punit-1.1.4.dist-info/WHEEL
punit-1.1.4.dist-info/entry_points.txt
punit-1.1.4.dist-info/top_level.txt
punit-1.1.4.dist-info/RECORD
