Metadata-Version: 2.4
Name: punit
Version: 1.1.4
Summary: A modernized unit-test framework for Python.
Author-email: Shaun Wilson <mrshaunwilson@msn.com>
Project-URL: Documentation, https://punit.readthedocs.io/
Project-URL: Homepage, https://github.com/wilson0x4d/punit
Project-URL: Repository, https://github.com/wilson0x4d/punit.git
Keywords: test,unittest,unit-test
Classifier: License :: OSI Approved :: MIT License
Classifier: Operating System :: OS Independent
Classifier: Programming Language :: Python :: 3.12
Classifier: Programming Language :: Python :: 3.13
Classifier: Topic :: Software Development :: Libraries :: Python Modules
Classifier: Intended Audience :: Developers
Requires-Python: >=3.12
License-File: LICENSE
Dynamic: license-file
